{
  "rules": [
    {
      "name": "Type Inheritance",
      "description": "Entities of a certain type are located in the same place.",
      "premises": [
        {
          "predicate": "located_in",
          "args": [
            "e1",
            "p"
          ]
        },
        {
          "predicate": "type_of",
          "args": [
            "e2",
            "t"
          ]
        },
        {
          "predicate": "type_of",
          "args": [
            "e1",
            "t"
          ]
        }
      ],
      "conclusion": {
        "predicate": "located_in",
        "args": [
          "e2",
          "p"
        ]
      }
    },
    {
      "name": "Authorship and Location",
      "description": "The author of a work is located in the same place as the work.",
      "premises": [
        {
          "predicate": "author_of",
          "args": [
            "a",
            "w"
          ]
        },
        {
          "predicate": "located_in",
          "args": [
            "a",
            "p"
          ]
        }
      ],
      "conclusion": {
        "predicate": "located_in",
        "args": [
          "w",
          "p"
        ]
      }
    },
    {
      "name": "Marriage and Location",
      "description": "The spouses of a person are located in the same place as that person.",
      "premises": [
        {
          "predicate": "married_to",
          "args": [
            "p1",
            "p2"
          ]
        },
        {
          "predicate": "located_in",
          "args": [
            "p1",
            "p"
          ]
        }
      ],
      "conclusion": {
        "predicate": "located_in",
        "args": [
          "p2",
          "p"
        ]
      }
    },
    {
      "name": "Starring and Location",
      "description": "The actor in a work is located in the same place as that work.",
      "premises": [
        {
          "predicate": "starred_in",
          "args": [
            "a",
            "w"
          ]
        },
        {
          "predicate": "located_in",
          "args": [
            "a",
            "p"
          ]
        }
      ],
      "conclusion": {
        "predicate": "located_in",
        "args": [
          "w",
          "p"
        ]
      }
    }
  ]
}